hcat_fusionnet-0.1.0.dist-info/licenses/LICENSE
hcat_preprocess/__init__.py
hcat_preprocess/clinical.py
hcat_preprocess/pathology.py
hcat_preprocess/semantic.py
hcat_preprocess/spatial.py
hcat_preprocess/temporal.py
hcat_fusionnet-0.1.0.dist-info/METADATA
hcat_fusionnet-0.1.0.dist-info/WHEEL
hcat_fusionnet-0.1.0.dist-info/top_level.txt
hcat_fusionnet-0.1.0.dist-info/RECORD
