Metadata-Version: 2.4
Name: hcat-fusionnet
Version: 0.1.0
Summary: Multimodal Preprocessing and Fusion for Survival and Recurrence Prediction using variational autoencoders and cross-modal attention.
Author: Ragunath R, Sanjay S, Harish G
License:                     GNU GENERAL PUBLIC LICENSE
Project-URL: Homepage, https://github.com/Ragu-123/hcat-fusionnet
Project-URL: Model Weights, https://huggingface.co/ragunath-ravi/hcat-fusionnet/tree/main/model/hcat_checkpoints_v_improved
Project-URL: HDF5 Files, https://huggingface.co/ragunath-ravi/hcat-fusionnet/tree/main/preprocessed_h5_files
Classifier: Programming Language :: Python :: 3
Classifier: License :: OSI Approved :: GNU General Public License v3 (GPLv3)
Classifier: Operating System :: OS Independent
Classifier: Topic :: Scientific/Engineering :: Medical Science Apps.
Classifier: Intended Audience :: Science/Research
Requires-Python: >=3.8
License-File: LICENSE
Requires-Dist: numpy
Requires-Dist: scipy
Requires-Dist: h5py
Requires-Dist: pandas
Requires-Dist: torch
Requires-Dist: scikit-learn
Requires-Dist: tqdm
Requires-Dist: transformers
Dynamic: license-file
